__init__.py
NumpyTransforms/Affine.py
NumpyTransforms/Bezier.py
NumpyTransforms/__init__.py
NumpyTransforms-0.0.1.dist-info/LICENSE
NumpyTransforms-0.0.1.dist-info/METADATA
NumpyTransforms-0.0.1.dist-info/WHEEL
NumpyTransforms-0.0.1.dist-info/top_level.txt
NumpyTransforms-0.0.1.dist-info/RECORD
