Metadata-Version: 2.1
Name: NumpyTransforms
Version: 0.0.1
Summary: Library of helpful transformations for numpy arrays
Author-email: Carter Bodinger <carterallenbodinger@yahoo.com>
License: GNU GENERAL PUBLIC LICENSE
Classifier: Programming Language :: Python :: 3
Classifier: License :: OSI Approved :: GNU General Public License v2 (GPLv2)
Classifier: Operating System :: OS Independent
Requires-Python: >=3.7
License-File: LICENSE
